MANIFEST.in
README.rst
setup.py
src/batchcompute/__init__.py
src/batchcompute.egg-info/PKG-INFO
src/batchcompute.egg-info/SOURCES.txt
src/batchcompute.egg-info/dependency_links.txt
src/batchcompute.egg-info/not-zip-safe
src/batchcompute.egg-info/requires.txt
src/batchcompute.egg-info/top_level.txt
src/batchcompute/client/__init__.py
src/batchcompute/client/client.py
src/batchcompute/client/response.py
src/batchcompute/core/__init__.py
src/batchcompute/core/api.py
src/batchcompute/core/exceptions.py
src/batchcompute/resources/__init__.py
src/batchcompute/resources/cluster.py
src/batchcompute/resources/image.py
src/batchcompute/resources/job.py
src/batchcompute/utils/__init__.py
src/batchcompute/utils/canonicalization.py
src/batchcompute/utils/constants.py
src/batchcompute/utils/functions.py
src/batchcompute/utils/http.py
src/batchcompute/utils/jsonizable.py
src/batchcompute/utils/log.py
tests/run_test.py
tests/client/__init__.py
tests/client/config.py
tests/client/test_client.py
tests/client/test_response.py
tests/resources/__init__.py
tests/resources/test_cluster.py
tests/resources/test_image.py
tests/resources/test_job.py
tests/utils/__init__.py
tests/utils/test_canonical.py
tests/utils/test_functions.py
tests/utils/test_jsonizable.py
tools/__init__.py
tools/ez_setup.py
tools/ez_setup_py25.py