Metadata-Version: 1.0
Name: batchcompute
Version: 2.0.4
Summary: Python SDK for aliyun batchcompute service
Home-page: UNKNOWN
Author: crisish <helei.hl@alibaba-inc.com>
Author-email: UNKNOWN
License: GPL v2.0
Platform: UNKNOWN
